screamlab/__init__.py
screamlab/dataset.py
screamlab/functions.py
screamlab/io.py
screamlab/settings.py
screamlab/utils.py
screamlab/__pycache__/__init__.cpython-310.pyc
screamlab/__pycache__/__init__.cpython-312.pyc
screamlab/__pycache__/__init__.cpython-313.pyc
screamlab/__pycache__/__init__.cpython-38.pyc
screamlab/__pycache__/dataset.cpython-310.pyc
screamlab/__pycache__/dataset.cpython-312.pyc
screamlab/__pycache__/dataset.cpython-313.pyc
screamlab/__pycache__/functions.cpython-310.pyc
screamlab/__pycache__/functions.cpython-312.pyc
screamlab/__pycache__/io.cpython-310.pyc
screamlab/__pycache__/io.cpython-312.pyc
screamlab/__pycache__/settings.cpython-310.pyc
screamlab/__pycache__/settings.cpython-312.pyc
screamlab/__pycache__/settings.cpython-313.pyc
screamlab/__pycache__/utils.cpython-310.pyc
screamlab/__pycache__/utils.cpython-312.pyc
screamlab-0.1.0.dist-info/licenses/LICENSE
screamlab-0.1.0.dist-info/METADATA
screamlab-0.1.0.dist-info/WHEEL
screamlab-0.1.0.dist-info/top_level.txt
screamlab-0.1.0.dist-info/RECORD
